db2qthelp.py
data/chunk_html.xsl
data/single_html.xsl
db2qthelp-0.4.0.dist-info/METADATA
db2qthelp-0.4.0.dist-info/WHEEL
db2qthelp-0.4.0.dist-info/entry_points.txt
db2qthelp-0.4.0.dist-info/top_level.txt
db2qthelp-0.4.0.dist-info/RECORD
