Metadata-Version: 2.4
Name: db2qthelp
Version: 0.4.0
Summary: A DocBook book to QtHelp converter
Home-page: http://db2qthelp.readthedocs.org/
Download-URL: http://pypi.python.org/pypi/db2qthelp
Author: dkrajzew
Author-email: d.krajzewicz@gmail.com
License: GPL
Project-URL: Documentation, https://db2qthelp.readthedocs.io/
Project-URL: Source, https://github.com/dkrajzew/db2qthelp
Project-URL: Tracker, https://github.com/dkrajzew/db2qthelp/issues
Project-URL: Discussions, https://github.com/dkrajzew/db2qthelp/discussions
Classifier: Development Status :: 2 - Pre-Alpha
Classifier: Environment :: Console
Classifier: Programming Language :: Python
Classifier: Programming Language :: Python :: 3
Classifier: Operating System :: OS Independent
Classifier: Intended Audience :: Developers
Classifier: Topic :: Software Development :: Libraries :: Python Modules
Classifier: Topic :: Documentation
Classifier: Topic :: Software Development
Classifier: Topic :: Text Processing :: Filters
Classifier: Topic :: Utilities
Requires-Python: >=3, <4
Dynamic: author
Dynamic: author-email
Dynamic: classifier
Dynamic: description
Dynamic: description-content-type
Dynamic: download-url
Dynamic: home-page
Dynamic: license
Dynamic: project-url
Dynamic: requires-python
Dynamic: summary
